pyeoskit/ABI.py
pyeoskit/__init__.py
pyeoskit/_pyeoskit.cp37-win_amd64.pyd
pyeoskit/block_log.py
pyeoskit/chainapi.py
pyeoskit/chainapi_async.py
pyeoskit/chainapi_sync.py
pyeoskit/chaincache.py
pyeoskit/chainnative.py
pyeoskit/common.py
pyeoskit/compiler.py
pyeoskit/config.py
pyeoskit/crypto.py
pyeoskit/defaultabi.py
pyeoskit/eosBase.py
pyeoskit/exceptions.py
pyeoskit/google_docstring.py
pyeoskit/http_client.py
pyeoskit/ledger.py
pyeoskit/log.py
pyeoskit/pyeoskit.dll
pyeoskit/rpc_interface.py
pyeoskit/test_helper.py
pyeoskit/testnet.py
pyeoskit/transaction.py
pyeoskit/utils.py
pyeoskit/wallet.py
pyeoskit/wasmcompiler.py
pyeoskit/contracts/eosio.bios/eosio.bios.abi
pyeoskit/contracts/eosio.bios/eosio.bios.wasm
pyeoskit/contracts/eosio.msig/eosio.msig.abi
pyeoskit/contracts/eosio.msig/eosio.msig.wasm
pyeoskit/contracts/eosio.system/eosio.system.abi
pyeoskit/contracts/eosio.system/eosio.system.wasm
pyeoskit/contracts/eosio.token/eosio.token.abi
pyeoskit/contracts/eosio.token/eosio.token.wasm
pyeoskit/contracts/eosio.wrap/eosio.wrap.abi
pyeoskit/contracts/eosio.wrap/eosio.wrap.wasm
pyeoskit/contracts/micropython/micropython.abi
pyeoskit/contracts/micropython/micropython.wasm
pyeoskit/contracts/micropython/micropython_eosio.wasm
pyeoskit/data/eosio.system_eosio.abi
pyeoskit/data/eosio.system_uuos.abi
pyeoskit/data/eosio.token.abi
pyeoskit-1.1.12.dist-info/LICENSE
pyeoskit-1.1.12.dist-info/METADATA
pyeoskit-1.1.12.dist-info/WHEEL
pyeoskit-1.1.12.dist-info/top_level.txt
pyeoskit-1.1.12.dist-info/RECORD
