Metadata-Version: 2.1
Name: pyeoskit
Version: 1.1.12
Summary: Python Toolkit for EOS
Home-page: https://github.com/learnforpractice/pyeoskit
Author: learnforpractice
License: MIT
Platform: UNKNOWN
License-File: LICENSE
Requires-Dist: requests-unixsocket (>=0.2.0)
Requires-Dist: httpx (>=0.19.0)
Requires-Dist: base58 (>=2.1.1)
Requires-Dist: asn1 (>=2.4.2)
Requires-Dist: ledgerblue (>=0.1.41)
